{"retrieved-date":"2025-04-07T17:49:35.770Z","videos":[{"channel-name":"MettaCode Developers","channel-id":"UCUrW7YMZDBaVMjP7V3XnpVw","channel-slug":"mettacode","channel-url":"https://www.youtube.com/channel/UCUrW7YMZDBaVMjP7V3XnpVw/videos","channel-videos":[]},{"channel-name":"Capitol Babble","channel-id":"UC4X_dh5dgyC0d6T3KkjFTTQ","channel-slug":"capitolbabble","channel-url":"https://www.youtube.com/channel/UC4X_dh5dgyC0d6T3KkjFTTQ/videos","channel-videos":[]},{"channel-name":"Bloomberg Politics","channel-id":"UCV61VqLMr2eIhH4f51PV0gA","channel-slug":"bloomberg","channel-url":"https://www.youtube.com/channel/UCV61VqLMr2eIhH4f51PV0gA/videos","channel-videos":[]},{"channel-name":"Politico","channel-id":"UCgjtvMmHXbutALaw9XzRkAg","channel-slug":"politico","channel-url":"https://www.youtube.com/channel/UCgjtvMmHXbutALaw9XzRkAg/videos","channel-videos":[{"channel":"Politico","title":"Trump on Russia-Ukraine peace talks: 'I don't like the bombing'","url":"https://www.youtube.com/watch?v=PgOZXPmgNio","id":"PgOZXPmgNio","date":"3 hours ago","thumbnail":"https://i.ytimg.com/vi/PgOZXPmgNio/hqdefault.jpg"},{"channel":"Politico","title":"Trump on measles outbreak: 'Not something new'","url":"https://www.youtube.com/watch?v=U9BsYJt1Sf4","id":"U9BsYJt1Sf4","date":"3 hours ago","thumbnail":"https://i.ytimg.com/vi/U9BsYJt1Sf4/hqdefault.jpg"},{"channel":"Politico","title":"Trump doubles down on tariffs as markets tumble","url":"https://www.youtube.com/watch?v=ocnJkDVD8VA","id":"ocnJkDVD8VA","date":"3 hours ago","thumbnail":"https://i.ytimg.com/vi/ocnJkDVD8VA/hqdefault.jpg"},{"channel":"Politico","title":"Trump on tariffs: 'Sometimes you have to take medicine'","url":"https://www.youtube.com/watch?v=lqdQaredJaw","id":"lqdQaredJaw","date":"4 hours ago","thumbnail":"https://i.ytimg.com/vi/lqdQaredJaw/hqdefault.jpg"},{"channel":"Politico","title":"Powell warns Trump’s tariffs raise risk of higher inflation","url":"https://www.youtube.com/watch?v=KIP7dgKgaiQ","id":"KIP7dgKgaiQ","date":"3 days ago","thumbnail":"https://i.ytimg.com/vi/KIP7dgKgaiQ/hqdefault.jpg"}]},{"channel-name":"C-SPAN","channel-id":"UCb--64Gl51jIEVE-GLDAVTg","channel-slug":"cspan","channel-url":"https://www.youtube.com/channel/UCb--64Gl51jIEVE-GLDAVTg/videos","channel-videos":[{"channel":"C-SPAN","title":"World Series Champion Los Angeles Dodgers visit White House","url":"https://www.youtube.com/watch?v=F238WJRBp7g","id":"F238WJRBp7g","date":"1 hour ago","thumbnail":"https://i.ytimg.com/vi/F238WJRBp7g/hqdefault.jpg"},{"channel":"C-SPAN","title":"New York AG Letitia James (D) on President Trump: \"Sincere ignorance and conscientious stupidity.\"","url":"https://www.youtube.com/watch?v=WOG1GbUxk_4","id":"WOG1GbUxk_4","date":"2 days ago","thumbnail":"https://i.ytimg.com/vi/WOG1GbUxk_4/hqdefault.jpg"},{"channel":"C-SPAN","title":"Washington Today (4-3-25): President Trump says tariff plan is 'going very well' as markets plummet","url":"https://www.youtube.com/watch?v=lkGyxr624Hw","id":"lkGyxr624Hw","date":"3 days ago","thumbnail":"https://i.ytimg.com/vi/lkGyxr624Hw/hqdefault.jpg"},{"channel":"C-SPAN","title":"Rep. John Larson (D-CT) on President Trump's Tariff Policies and Social Security","url":"https://www.youtube.com/watch?v=MtcmxGLzh-o&pp=0gcJCX4JAYcqIYzv","id":"MtcmxGLzh-o&pp=0gcJCX4JAYcqIYzv","date":"4 days ago","thumbnail":"https://i.ytimg.com/vi/MtcmxGLzh-o&pp=0gcJCX4JAYcqIYzv/hqdefault.jpg"},{"channel":"C-SPAN","title":"Rep. John McGuire on Trump Tariffs and DOGE Efforts","url":"https://www.youtube.com/watch?v=x641mFngJCA","id":"x641mFngJCA","date":"4 days ago","thumbnail":"https://i.ytimg.com/vi/x641mFngJCA/hqdefault.jpg"},{"channel":"C-SPAN","title":"President Trump Signs Executive Orders Imposing Tariffs","url":"https://www.youtube.com/watch?v=z3OxZOEbDwQ","id":"z3OxZOEbDwQ","date":"4 days ago","thumbnail":"https://i.ytimg.com/vi/z3OxZOEbDwQ/hqdefault.jpg"}]},{"channel-name":"Epoch TV","channel-id":"UCr9eziCDBtDANyWguKLr4vg","channel-slug":"epochtv","channel-url":"https://www.youtube.com/channel/UCr9eziCDBtDANyWguKLr4vg/videos","channel-videos":[{"channel":"Epoch TV","title":"Global Markets React to Trump’s Sweeping Tariffs That Target Decades of Unfair Trade | CLIP","url":"https://www.youtube.com/watch?v=4wpKYLUlKMg","id":"4wpKYLUlKMg","date":"2 days ago","thumbnail":"https://i.ytimg.com/vi/4wpKYLUlKMg/hqdefault.jpg"},{"channel":"Epoch TV","title":"Trump Unveils ‘Liberation Day’ Tariffs to Promote US Manufacturing | CLIP | Capitol Report","url":"https://www.youtube.com/watch?v=kDQ4joD84cI","id":"kDQ4joD84cI","date":"3 days ago","thumbnail":"https://i.ytimg.com/vi/kDQ4joD84cI/hqdefault.jpg"},{"channel":"Epoch TV","title":"'Liberation Day' Tariffs to Kick In; TikTok Deadline Looms | CLIP | Capitol Report","url":"https://www.youtube.com/watch?v=A8-OZLq51Rc","id":"A8-OZLq51Rc","date":"4 days ago","thumbnail":"https://i.ytimg.com/vi/A8-OZLq51Rc/hqdefault.jpg"},{"channel":"Epoch TV","title":"EO Targeting Ticket Price Gouging | Strengthening the Alliance | Clip | Capitol Report","url":"https://www.youtube.com/watch?v=ysR0neRgYys","id":"ysR0neRgYys","date":"5 days ago","thumbnail":"https://i.ytimg.com/vi/ysR0neRgYys/hqdefault.jpg"},{"channel":"Epoch TV","title":"Trump Mandates Proof of Citizenship for Elections | CLIP | Crossroads","url":"https://www.youtube.com/watch?v=XJH26w7ob8c","id":"XJH26w7ob8c","date":"6 days ago","thumbnail":"https://i.ytimg.com/vi/XJH26w7ob8c/hqdefault.jpg"},{"channel":"Epoch TV","title":"Vance and Wife Visit US Military Base in Greenland | Clip | Capitol Report","url":"https://www.youtube.com/watch?v=9d7ToI94ABc","id":"9d7ToI94ABc","date":"6 days ago","thumbnail":"https://i.ytimg.com/vi/9d7ToI94ABc/hqdefault.jpg"},{"channel":"Epoch TV","title":"Will Democrats Flip Congress in Midterm? | Tariff & Venezuelan Oil | Clip | Capitol Report","url":"https://www.youtube.com/watch?v=2CzvICzCFo8","id":"2CzvICzCFo8","date":"9 days ago","thumbnail":"https://i.ytimg.com/vi/2CzvICzCFo8/hqdefault.jpg"}]},{"channel-name":"Propublica","channel-id":"UCtCL58_DaVdVRmev3yHK7pg","channel-slug":"propublica","channel-url":"https://www.youtube.com/channel/UCtCL58_DaVdVRmev3yHK7pg/videos","channel-videos":[]},{"channel-name":"USA Today","channel-id":"UCP6HGa63sBC7-KHtkme-p-g","channel-slug":"usatoday","channel-url":"https://www.youtube.com/channel/UCP6HGa63sBC7-KHtkme-p-g/videos","channel-videos":[{"channel":"USA Today","title":"Trump defends tariffs amid market mayhem | The Excerpt","url":"https://www.youtube.com/watch?v=1QOaGdM5i9Y","id":"1QOaGdM5i9Y","date":"7 hours ago","thumbnail":"https://i.ytimg.com/vi/1QOaGdM5i9Y/hqdefault.jpg"},{"channel":"USA Today","title":"Major stock indexes have worst day in years | The Excerpt","url":"https://www.youtube.com/watch?v=hX6t4hlI8Yk","id":"hX6t4hlI8Yk","date":"3 days ago","thumbnail":"https://i.ytimg.com/vi/hX6t4hlI8Yk/hqdefault.jpg"},{"channel":"USA Today","title":"Deportations and revoked visas: What is Trump's immigration endgame? | USA TODAY","url":"https://www.youtube.com/watch?v=UbeAzv2wy3E","id":"UbeAzv2wy3E","date":"3 days ago","thumbnail":"https://i.ytimg.com/vi/UbeAzv2wy3E/hqdefault.jpg"}]},{"channel-name":"Forbes Breaking","channel-id":"UCg40OxZ1GYh3u3jBntB6DLg","channel-slug":"forbes","channel-url":"https://www.youtube.com/channel/UCg40OxZ1GYh3u3jBntB6DLg/videos","channel-videos":[{"channel":"Forbes Breaking","title":"JUST IN: President Trump Welcomes Israeli PM Benjamin Netanyahu To The White House","url":"https://www.youtube.com/watch?v=XxfeyEQpApE","id":"XxfeyEQpApE","date":"3 minutes ago","thumbnail":"https://i.ytimg.com/vi/XxfeyEQpApE/hqdefault.jpg"},{"channel":"Forbes Breaking","title":"'This Is Insane': Trump Tariffs Risk 'Economic Catastrophe,' Warns Hedge Fund Founder","url":"https://www.youtube.com/watch?v=JubvhXaOO40","id":"JubvhXaOO40","date":"7 minutes ago","thumbnail":"https://i.ytimg.com/vi/JubvhXaOO40/hqdefault.jpg"},{"channel":"Forbes Breaking","title":"Mike Rounds Asks Trump’s JCS Nom About Protecting Military Access To The Electromagnetic Spectrum","url":"https://www.youtube.com/watch?v=dkZH2OF6P5Y","id":"dkZH2OF6P5Y","date":"20 minutes ago","thumbnail":"https://i.ytimg.com/vi/dkZH2OF6P5Y/hqdefault.jpg"},{"channel":"Forbes Breaking","title":"EU's Ursula von der Leyen Announces Potential 'Countermeasures' To President Trump's Tariffs","url":"https://www.youtube.com/watch?v=qrXhJMS9P70","id":"qrXhJMS9P70","date":"26 minutes ago","thumbnail":"https://i.ytimg.com/vi/qrXhJMS9P70/hqdefault.jpg"},{"channel":"Forbes Breaking","title":"BREAKING NEWS: President Trump Threatens China With Additional 50% Tariff","url":"https://www.youtube.com/watch?v=xgIoBQl_MAE","id":"xgIoBQl_MAE","date":"43 minutes ago","thumbnail":"https://i.ytimg.com/vi/xgIoBQl_MAE/hqdefault.jpg"},{"channel":"Forbes Breaking","title":"Robert Garcia Rails Against 'Donald Trump, Elon Musk, And Their Disastrous MAGA-Nomics'","url":"https://www.youtube.com/watch?v=xnUPY8d7snQ","id":"xnUPY8d7snQ","date":"45 minutes ago","thumbnail":"https://i.ytimg.com/vi/xnUPY8d7snQ/hqdefault.jpg"}]},{"channel-name":"Valuetainment","channel-id":"UCIHdDJ0tjn_3j-FS7s_X1kQ","channel-slug":"Valuetainment","channel-url":"https://www.youtube.com/channel/UCIHdDJ0tjn_3j-FS7s_X1kQ/videos","channel-videos":[{"channel":"Valuetainment","title":"\"Newton’s Law Of Gravity Is WRONG\" - Terrence Howard’s Theory That Could Change Physics FOREVER!","url":"https://www.youtube.com/watch?v=2c3HPxDA4fk","id":"2c3HPxDA4fk","date":"2 days ago","thumbnail":"https://i.ytimg.com/vi/2c3HPxDA4fk/hqdefault.jpg"}]}]}