{"retrieved-date":"2023-05-16T06:38:43.174Z","videos":[{"channel-name":"MettaCode Developers","channel-id":"UCUrW7YMZDBaVMjP7V3XnpVw","channel-slug":"mettacode","channel-url":"https://www.youtube.com/channel/UCUrW7YMZDBaVMjP7V3XnpVw/videos","channel-videos":[]},{"channel-name":"Capitol Babble","channel-id":"UC4X_dh5dgyC0d6T3KkjFTTQ","channel-slug":"capitolbabble","channel-url":"https://www.youtube.com/channel/UC4X_dh5dgyC0d6T3KkjFTTQ/videos","channel-videos":[]},{"channel-name":"Bloomberg Politics","channel-id":"UCV61VqLMr2eIhH4f51PV0gA","channel-slug":"bloomberg","channel-url":"https://www.youtube.com/channel/UCV61VqLMr2eIhH4f51PV0gA/videos","channel-videos":[]},{"channel-name":"Politico","channel-id":"UCgjtvMmHXbutALaw9XzRkAg","channel-slug":"politico","channel-url":"https://www.youtube.com/channel/UCgjtvMmHXbutALaw9XzRkAg/videos","channel-videos":[]},{"channel-name":"C-SPAN","channel-id":"UCb--64Gl51jIEVE-GLDAVTg","channel-slug":"cspan","channel-url":"https://www.youtube.com/channel/UCb--64Gl51jIEVE-GLDAVTg/videos","channel-videos":[{"channel":"C-SPAN","title":"Washington Today (5/15/2023): POTUS Biden, House Republicans prepare for US debt-ceiling talks","url":"https://www.youtube.com/watch?v=WAabtGkdRlw","id":"WAabtGkdRlw","date":"8 hours ago","thumbnail":"https://i.ytimg.com/vi/WAabtGkdRlw/hqdefault.jpg"},{"channel":"C-SPAN","title":"Washington Today (5-11-23): House passes immigration bill on party lines as Title 42 expires","url":"https://www.youtube.com/watch?v=oaCggtc6YNA","id":"oaCggtc6YNA","date":"4 days ago","thumbnail":"https://i.ytimg.com/vi/oaCggtc6YNA/hqdefault.jpg"},{"channel":"C-SPAN","title":"The Weekly Podcast: Writers Strike, But Congress Tells Their Late-Night TV Jokes","url":"https://www.youtube.com/watch?v=W6jZbV5Kx8k","id":"W6jZbV5Kx8k","date":"4 days ago","thumbnail":"https://i.ytimg.com/vi/W6jZbV5Kx8k/hqdefault.jpg"},{"channel":"C-SPAN","title":"Washington Today (5-9-23): President Biden, Speaker McCarthy meet on debt limit; no deal yet","url":"https://www.youtube.com/watch?v=Bic2bg9Zvcs","id":"Bic2bg9Zvcs","date":"6 days ago","thumbnail":"https://i.ytimg.com/vi/Bic2bg9Zvcs/hqdefault.jpg"},{"channel":"C-SPAN","title":"Former Attorney General Bill Barr: \"Trump will not deliver Trump policies. He will deliver chaos.\"","url":"https://www.youtube.com/watch?v=mhe0amOv5Lw","id":"mhe0amOv5Lw","date":"10 days ago","thumbnail":"https://i.ytimg.com/vi/mhe0amOv5Lw/hqdefault.jpg"},{"channel":"C-SPAN","title":"Washington Today (5-2-23): Partisan split at Senate committee hearing on Supreme Court ethics","url":"https://www.youtube.com/watch?v=VGur8JIvG4U","id":"VGur8JIvG4U","date":"13 days ago","thumbnail":"https://i.ytimg.com/vi/VGur8JIvG4U/hqdefault.jpg"}]},{"channel-name":"Epoch TV","channel-id":"UCr9eziCDBtDANyWguKLr4vg","channel-slug":"epochtv","channel-url":"https://www.youtube.com/channel/UCr9eziCDBtDANyWguKLr4vg/videos","channel-videos":[{"channel":"Epoch TV","title":"Are Republican Attacks on MAGA Making Trump Only Stronger? | CLIP | Crossroads","url":"https://www.youtube.com/watch?v=hv8joPBXkdA","id":"hv8joPBXkdA","date":"5 days ago","thumbnail":"https://i.ytimg.com/vi/hv8joPBXkdA/hqdefault.jpg"},{"channel":"Epoch TV","title":"Death Penalty for Child Rapists: New Law Goes Into Effect in Florida | CLIP | Facts Matter","url":"https://www.youtube.com/watch?v=m4HMsHS1NJk","id":"m4HMsHS1NJk","date":"6 days ago","thumbnail":"https://i.ytimg.com/vi/m4HMsHS1NJk/hqdefault.jpg"}]},{"channel-name":"Propublica","channel-id":"UCtCL58_DaVdVRmev3yHK7pg","channel-slug":"propublica","channel-url":"https://www.youtube.com/channel/UCtCL58_DaVdVRmev3yHK7pg/videos","channel-videos":[]},{"channel-name":"USA Today","channel-id":"UCP6HGa63sBC7-KHtkme-p-g","channel-slug":"usatoday","channel-url":"https://www.youtube.com/channel/UCP6HGa63sBC7-KHtkme-p-g/videos","channel-videos":[{"channel":"USA Today","title":"Biden to Howard graduates: January 6 put dagger at democracy throat | USA TODAY","url":"https://www.youtube.com/watch?v=Sd6t5pY3p7E","id":"Sd6t5pY3p7E","date":"2 days ago","thumbnail":"https://i.ytimg.com/vi/Sd6t5pY3p7E/hqdefault.jpg"}]}]}