{"retrieved-date":"2024-11-04T20:06:11.576Z","videos":[{"channel-name":"MettaCode Developers","channel-id":"UCUrW7YMZDBaVMjP7V3XnpVw","channel-slug":"mettacode","channel-url":"https://www.youtube.com/channel/UCUrW7YMZDBaVMjP7V3XnpVw/videos","channel-videos":[]},{"channel-name":"Capitol Babble","channel-id":"UC4X_dh5dgyC0d6T3KkjFTTQ","channel-slug":"capitolbabble","channel-url":"https://www.youtube.com/channel/UC4X_dh5dgyC0d6T3KkjFTTQ/videos","channel-videos":[]},{"channel-name":"Bloomberg Politics","channel-id":"UCV61VqLMr2eIhH4f51PV0gA","channel-slug":"bloomberg","channel-url":"https://www.youtube.com/channel/UCV61VqLMr2eIhH4f51PV0gA/videos","channel-videos":[]},{"channel-name":"Politico","channel-id":"UCgjtvMmHXbutALaw9XzRkAg","channel-slug":"politico","channel-url":"https://www.youtube.com/channel/UCgjtvMmHXbutALaw9XzRkAg/videos","channel-videos":[{"channel":"Politico","title":"Top contentious ballot measures that could bring drastic policy changes","url":"https://www.youtube.com/watch?v=w83Xf2H3yaw","id":"w83Xf2H3yaw","date":"3 days ago","thumbnail":"https://i.ytimg.com/vi/w83Xf2H3yaw/hqdefault.jpg"},{"channel":"Politico","title":"'Zombie' Nikki Haley voters and four other crucial voting blocs this election","url":"https://www.youtube.com/watch?v=xvUR2f9dvFE","id":"xvUR2f9dvFE","date":"3 days ago","thumbnail":"https://i.ytimg.com/vi/xvUR2f9dvFE/hqdefault.jpg"},{"channel":"Politico","title":"The last-minute race for 'the bro vote,' explained","url":"https://www.youtube.com/watch?v=YDayYWDf_BM","id":"YDayYWDf_BM","date":"4 days ago","thumbnail":"https://i.ytimg.com/vi/YDayYWDf_BM/hqdefault.jpg"},{"channel":"Politico","title":"Harris distances herself from Biden's 'garbage' gaffe","url":"https://www.youtube.com/watch?v=8WX3WZ6i4GE","id":"8WX3WZ6i4GE","date":"5 days ago","thumbnail":"https://i.ytimg.com/vi/8WX3WZ6i4GE/hqdefault.jpg"},{"channel":"Politico","title":"Did Biden’s ‘garbage’ gaffe upstage Harris's closing argument? | Playbook Daily Briefing","url":"https://www.youtube.com/watch?v=SwiMsywebHE","id":"SwiMsywebHE","date":"5 days ago","thumbnail":"https://i.ytimg.com/vi/SwiMsywebHE/hqdefault.jpg"},{"channel":"Politico","title":"Rubio says Biden called Trump supporters 'garbage'","url":"https://www.youtube.com/watch?v=DaAk-WHku3g","id":"DaAk-WHku3g","date":"5 days ago","thumbnail":"https://i.ytimg.com/vi/DaAk-WHku3g/hqdefault.jpg"},{"channel":"Politico","title":"'Petty tyrant': Harris uses closing argument to paint contrast with Trump","url":"https://www.youtube.com/watch?v=QQvS6IS6L0U","id":"QQvS6IS6L0U","date":"5 days ago","thumbnail":"https://i.ytimg.com/vi/QQvS6IS6L0U/hqdefault.jpg"},{"channel":"Politico","title":"Trump touts MSG rally as 'lovefest,' slams Nazi comparison","url":"https://www.youtube.com/watch?v=RlMHh09aM3M","id":"RlMHh09aM3M","date":"6 days ago","thumbnail":"https://i.ytimg.com/vi/RlMHh09aM3M/hqdefault.jpg"},{"channel":"Politico","title":"We likely won't get results on election night. Here are 3 reasons why.","url":"https://www.youtube.com/watch?v=NaLLlNJI12k","id":"NaLLlNJI12k","date":"6 days ago","thumbnail":"https://i.ytimg.com/vi/NaLLlNJI12k/hqdefault.jpg"},{"channel":"Politico","title":"Dems unleash on GOP after racist remarks at Trump MSG event","url":"https://www.youtube.com/watch?v=mWW86PP1BCA","id":"mWW86PP1BCA","date":"7 days ago","thumbnail":"https://i.ytimg.com/vi/mWW86PP1BCA/hqdefault.jpg"}]},{"channel-name":"C-SPAN","channel-id":"UCb--64Gl51jIEVE-GLDAVTg","channel-slug":"cspan","channel-url":"https://www.youtube.com/channel/UCb--64Gl51jIEVE-GLDAVTg/videos","channel-videos":[{"channel":"C-SPAN","title":"Former President Trump on Bulletproof Glass","url":"https://www.youtube.com/watch?v=hIGEgB6iazc","id":"hIGEgB6iazc","date":"19 hours ago","thumbnail":"https://i.ytimg.com/vi/hIGEgB6iazc/hqdefault.jpg"},{"channel":"C-SPAN","title":"Washington Today (11-1-24): Donald Trump doubles down on Liz Cheney 'rifles shooting at her' comment","url":"https://www.youtube.com/watch?v=HCOxY6ipQkw","id":"HCOxY6ipQkw","date":"2 days ago","thumbnail":"https://i.ytimg.com/vi/HCOxY6ipQkw/hqdefault.jpg"},{"channel":"C-SPAN","title":"Former President Trump on Rep. Liz Cheney: \"She's a war hawk..She's actually a disgrace.\"","url":"https://www.youtube.com/watch?v=uxeELS78BAE","id":"uxeELS78BAE","date":"3 days ago","thumbnail":"https://i.ytimg.com/vi/uxeELS78BAE/hqdefault.jpg"},{"channel":"C-SPAN","title":"VP Harris on Trump's Comments on Rep. Liz Cheney: \"This must be disqualifying.\"","url":"https://www.youtube.com/watch?v=UaI1-OAZH7g","id":"UaI1-OAZH7g","date":"3 days ago","thumbnail":"https://i.ytimg.com/vi/UaI1-OAZH7g/hqdefault.jpg"},{"channel":"C-SPAN","title":"Trump on Liz Cheney: \"Let’s put her with a rifle standing there with nine barrels shooting at her\"","url":"https://www.youtube.com/watch?v=6VHP68I2j2w","id":"6VHP68I2j2w","date":"3 days ago","thumbnail":"https://i.ytimg.com/vi/6VHP68I2j2w/hqdefault.jpg"},{"channel":"C-SPAN","title":"Washington Today (10-31-24): Kamala Harris reacts to Donald Trump's  'whether women like it or not'","url":"https://www.youtube.com/watch?v=5Azsy5damOc","id":"5Azsy5damOc","date":"3 days ago","thumbnail":"https://i.ytimg.com/vi/5Azsy5damOc/hqdefault.jpg"},{"channel":"C-SPAN","title":"Former President Trump in Garbage Truck","url":"https://www.youtube.com/watch?v=kzcJovV4FOM","id":"kzcJovV4FOM","date":"4 days ago","thumbnail":"https://i.ytimg.com/vi/kzcJovV4FOM/hqdefault.jpg"},{"channel":"C-SPAN","title":"Washington Today (10-30-24): Donald Trump & Kamala Harris react to Pres. Biden's 'garbage' comment","url":"https://www.youtube.com/watch?v=vCZGWXpNMS0","id":"vCZGWXpNMS0","date":"4 days ago","thumbnail":"https://i.ytimg.com/vi/vCZGWXpNMS0/hqdefault.jpg"},{"channel":"C-SPAN","title":"Vice President Harris Responds to President Biden's 'Garbage' Comments","url":"https://www.youtube.com/watch?v=PRLzkumWhfE","id":"PRLzkumWhfE","date":"5 days ago","thumbnail":"https://i.ytimg.com/vi/PRLzkumWhfE/hqdefault.jpg"},{"channel":"C-SPAN","title":"Former President Donald Trump: \"You can't lead America if you don't love Americans.\"","url":"https://www.youtube.com/watch?v=G-Cx9IlUfUY","id":"G-Cx9IlUfUY","date":"5 days ago","thumbnail":"https://i.ytimg.com/vi/G-Cx9IlUfUY/hqdefault.jpg"}]},{"channel-name":"Epoch TV","channel-id":"UCr9eziCDBtDANyWguKLr4vg","channel-slug":"epochtv","channel-url":"https://www.youtube.com/channel/UCr9eziCDBtDANyWguKLr4vg/videos","channel-videos":[{"channel":"Epoch TV","title":"Republicans and Democrats Prepare for Challenges to 2024 Election | CLIP | Crossroads","url":"https://www.youtube.com/watch?v=oBdNP17QFYw","id":"oBdNP17QFYw","date":"12 days ago","thumbnail":"https://i.ytimg.com/vi/oBdNP17QFYw/hqdefault.jpg"}]},{"channel-name":"Propublica","channel-id":"UCtCL58_DaVdVRmev3yHK7pg","channel-slug":"propublica","channel-url":"https://www.youtube.com/channel/UCtCL58_DaVdVRmev3yHK7pg/videos","channel-videos":[{"channel":"Propublica","title":"\"If they're illegal aliens, they're not going to be able to register to vote\"","url":"https://www.youtube.com/watch?v=W0-JW1qj3j8","id":"W0-JW1qj3j8","date":"2 hours ago","thumbnail":"https://i.ytimg.com/vi/W0-JW1qj3j8/hqdefault.jpg"},{"channel":"Propublica","title":"In the Age of Trump, the Business Lobby Has Strayed from Immigration Reform","url":"https://www.youtube.com/watch?v=4q7YdrmXJCk","id":"4q7YdrmXJCk","date":"6 days ago","thumbnail":"https://i.ytimg.com/vi/4q7YdrmXJCk/hqdefault.jpg"}]},{"channel-name":"USA Today","channel-id":"UCP6HGa63sBC7-KHtkme-p-g","channel-slug":"usatoday","channel-url":"https://www.youtube.com/channel/UCP6HGa63sBC7-KHtkme-p-g/videos","channel-videos":[{"channel":"USA Today","title":"Georgia officials promise safe and speedy voting ahead of election day | USA TODAY","url":"https://www.youtube.com/watch?v=uwB_gDm9FTM","id":"uwB_gDm9FTM","date":"8 minutes ago","thumbnail":"https://i.ytimg.com/vi/uwB_gDm9FTM/hqdefault.jpg"},{"channel":"USA Today","title":"Are banks and post offices open on Election Day? | USA TODAY","url":"https://www.youtube.com/watch?v=bcL4w8oyPmI","id":"bcL4w8oyPmI","date":"21 minutes ago","thumbnail":"https://i.ytimg.com/vi/bcL4w8oyPmI/hqdefault.jpg"},{"channel":"USA Today","title":"Where Kamala Harris, Donald Trump stand on top election issues","url":"https://www.youtube.com/watch?v=aC6X9fIKjSA","id":"aC6X9fIKjSA","date":"2 hours ago","thumbnail":"https://i.ytimg.com/vi/aC6X9fIKjSA/hqdefault.jpg"},{"channel":"USA Today","title":"Americans vote on abortion, immigration, marijuana and voting rights | USA TODAY","url":"https://www.youtube.com/watch?v=zHsPj6loNrQ","id":"zHsPj6loNrQ","date":"3 hours ago","thumbnail":"https://i.ytimg.com/vi/zHsPj6loNrQ/hqdefault.jpg"},{"channel":"USA Today","title":"Trump ramped up violent rhetoric while Harris appealed to young voters | USA TODAY","url":"https://www.youtube.com/watch?v=x2Nt4btM5es","id":"x2Nt4btM5es","date":"5 hours ago","thumbnail":"https://i.ytimg.com/vi/x2Nt4btM5es/hqdefault.jpg"},{"channel":"USA Today","title":"Trump says he \"shouldn't have left\" White House in 2020; Harris pitches Gen Z voters | The Excerpt","url":"https://www.youtube.com/watch?v=WQIeRSWmVTo","id":"WQIeRSWmVTo","date":"9 hours ago","thumbnail":"https://i.ytimg.com/vi/WQIeRSWmVTo/hqdefault.jpg"},{"channel":"USA Today","title":"This is how some fans feel about Taylor Swift getting political | USA TODAY","url":"https://www.youtube.com/watch?v=oMbEadaaC7w","id":"oMbEadaaC7w","date":"18 hours ago","thumbnail":"https://i.ytimg.com/vi/oMbEadaaC7w/hqdefault.jpg"},{"channel":"USA Today","title":"Election anxiety is gripping the nation | The Excerpt","url":"https://www.youtube.com/watch?v=ic7EjxhS1aA","id":"ic7EjxhS1aA","date":"1 day ago","thumbnail":"https://i.ytimg.com/vi/ic7EjxhS1aA/hqdefault.jpg"},{"channel":"USA Today","title":"These iconic political moments have shaped the 2024 elections | USA TODAY","url":"https://www.youtube.com/watch?v=wDAzbczjcm0","id":"wDAzbczjcm0","date":"2 days ago","thumbnail":"https://i.ytimg.com/vi/wDAzbczjcm0/hqdefault.jpg"}]},{"channel-name":"Forbes Breaking","channel-id":"UCg40OxZ1GYh3u3jBntB6DLg","channel-slug":"forbes","channel-url":"https://www.youtube.com/channel/UCg40OxZ1GYh3u3jBntB6DLg/videos","channel-videos":[{"channel":"Forbes Breaking","title":"'Now I Don't Have To Carry Around That Story': Trump Complains About Van Jones At NC Rally","url":"https://www.youtube.com/watch?v=BQJjSzdDKGw","id":"BQJjSzdDKGw","date":"10 minutes ago","thumbnail":"https://i.ytimg.com/vi/BQJjSzdDKGw/hqdefault.jpg"},{"channel":"Forbes Breaking","title":"FULL EVENT: Trump Holds Last Campaign Rally In North Carolina Before Election Day","url":"https://www.youtube.com/watch?v=HtcDDDw0kCY","id":"HtcDDDw0kCY","date":"11 minutes ago","thumbnail":"https://i.ytimg.com/vi/HtcDDDw0kCY/hqdefault.jpg"},{"channel":"Forbes Breaking","title":"New York City Mayor Eric Adams Holds Press Briefing Ahead Of Election Day","url":"https://www.youtube.com/watch?v=o_VSoOXUnNs","id":"o_VSoOXUnNs","date":"16 minutes ago","thumbnail":"https://i.ytimg.com/vi/o_VSoOXUnNs/hqdefault.jpg"},{"channel":"Forbes Breaking","title":"BREAKING: JD Vance Makes Final Appeal To Voters In Flint, Michigan Ahead Of Election Day","url":"https://www.youtube.com/watch?v=D1vdflu_6cU","id":"D1vdflu_6cU","date":"30 minutes ago","thumbnail":"https://i.ytimg.com/vi/D1vdflu_6cU/hqdefault.jpg"},{"channel":"Forbes Breaking","title":"'That's How You Vote 10 Times': JD Vance Calls On Voters To Bring Friends And Family To Polls","url":"https://www.youtube.com/watch?v=5lXXTLo87e8","id":"5lXXTLo87e8","date":"36 minutes ago","thumbnail":"https://i.ytimg.com/vi/5lXXTLo87e8/hqdefault.jpg"},{"channel":"Forbes Breaking","title":"JUST IN: Michigan Secretary Of State Jocelyn Benson Holds Press Conference Ahead Of The Election","url":"https://www.youtube.com/watch?v=Ow0R4CApRME","id":"Ow0R4CApRME","date":"1 hour ago","thumbnail":"https://i.ytimg.com/vi/Ow0R4CApRME/hqdefault.jpg"},{"channel":"Forbes Breaking","title":"JUST IN: Tim Walz Rallies Supporters In La Crosse, Wisconsin As Election Enters Final Stretch","url":"https://www.youtube.com/watch?v=ADcX4sCKhJQ","id":"ADcX4sCKhJQ","date":"1 hour ago","thumbnail":"https://i.ytimg.com/vi/ADcX4sCKhJQ/hqdefault.jpg"},{"channel":"Forbes Breaking","title":"WATCH: Sarah Huckabee Sanders, Marco Rubio Join Trump In Final Hours Of 2024 Campaign","url":"https://www.youtube.com/watch?v=S5_ttcJ3L3g","id":"S5_ttcJ3L3g","date":"1 hour ago","thumbnail":"https://i.ytimg.com/vi/S5_ttcJ3L3g/hqdefault.jpg"},{"channel":"Forbes Breaking","title":"'Michelle Hit Me... Am I Allowed To Hit Her Now?': Trump Takes Aim At Michelle Obama At NC Rally","url":"https://www.youtube.com/watch?v=Bigq3voyrn4","id":"Bigq3voyrn4","date":"1 hour ago","thumbnail":"https://i.ytimg.com/vi/Bigq3voyrn4/hqdefault.jpg"}]},{"channel-name":"Valuetainment","channel-id":"UCIHdDJ0tjn_3j-FS7s_X1kQ","channel-slug":"Valuetainment","channel-url":"https://www.youtube.com/channel/UCIHdDJ0tjn_3j-FS7s_X1kQ/videos","channel-videos":[{"channel":"Valuetainment","title":"\"Trump Almost Made Iran FALL!\" - Reza Pahlavi Says Trump's Nuclear Sanctions CRIPPLED Iran's Economy","url":"https://www.youtube.com/watch?v=L-mZwJgfsYA","id":"L-mZwJgfsYA","date":"2 hours ago","thumbnail":"https://i.ytimg.com/vi/L-mZwJgfsYA/hqdefault.jpg"},{"channel":"Valuetainment","title":"“Body Language” - 25 Reasons Trump Will Win The 2024 Election Barring a Black Swan Event","url":"https://www.youtube.com/watch?v=g1cVjre4n_E","id":"g1cVjre4n_E","date":"6 hours ago","thumbnail":"https://i.ytimg.com/vi/g1cVjre4n_E/hqdefault.jpg"},{"channel":"Valuetainment","title":"“Abusing War Oil Reserves” - Dems Strategy to Drop Gas Prices EXPOSED","url":"https://www.youtube.com/watch?v=2-xMFaB-aUU","id":"2-xMFaB-aUU","date":"2 days ago","thumbnail":"https://i.ytimg.com/vi/2-xMFaB-aUU/hqdefault.jpg"},{"channel":"Valuetainment","title":"\"Trump Tariffs IMPACT!\" - China Delays Hofusan Mexico Factory Amid U.S. Election Uncertainty","url":"https://www.youtube.com/watch?v=iF8B_9_6NwY","id":"iF8B_9_6NwY","date":"3 days ago","thumbnail":"https://i.ytimg.com/vi/iF8B_9_6NwY/hqdefault.jpg"},{"channel":"Valuetainment","title":"\"Wedge Between Elon and Trump\" - Suspicious Timing As Truth Social's Valuation SKYROCKETS Over X","url":"https://www.youtube.com/watch?v=hAO6vOu7lu4","id":"hAO6vOu7lu4","date":"3 days ago","thumbnail":"https://i.ytimg.com/vi/hAO6vOu7lu4/hqdefault.jpg"},{"channel":"Valuetainment","title":"\"Proud I Killed Them!\" - Trump CRUSHES Fake News As Trust In Media Hits ALL TIME LOW!","url":"https://www.youtube.com/watch?v=w1mbxwZ5FQ4","id":"w1mbxwZ5FQ4","date":"3 days ago","thumbnail":"https://i.ytimg.com/vi/w1mbxwZ5FQ4/hqdefault.jpg"}]}]}