{"retrieved-date":"2024-08-30T19:12:18.413Z","videos":[{"channel-name":"MettaCode Developers","channel-id":"UCUrW7YMZDBaVMjP7V3XnpVw","channel-slug":"mettacode","channel-url":"https://www.youtube.com/channel/UCUrW7YMZDBaVMjP7V3XnpVw/videos","channel-videos":[]},{"channel-name":"Capitol Babble","channel-id":"UC4X_dh5dgyC0d6T3KkjFTTQ","channel-slug":"capitolbabble","channel-url":"https://www.youtube.com/channel/UC4X_dh5dgyC0d6T3KkjFTTQ/videos","channel-videos":[]},{"channel-name":"Bloomberg Politics","channel-id":"UCV61VqLMr2eIhH4f51PV0gA","channel-slug":"bloomberg","channel-url":"https://www.youtube.com/channel/UCV61VqLMr2eIhH4f51PV0gA/videos","channel-videos":[]},{"channel-name":"Politico","channel-id":"UCgjtvMmHXbutALaw9XzRkAg","channel-slug":"politico","channel-url":"https://www.youtube.com/channel/UCgjtvMmHXbutALaw9XzRkAg/videos","channel-videos":[{"channel":"Politico","title":"Trump on Harris' CNN interview: 'She didn't look like a leader'","url":"https://www.youtube.com/watch?v=fYVbRrWt9M4","id":"fYVbRrWt9M4","date":"4 hours ago","thumbnail":"https://i.ytimg.com/vi/fYVbRrWt9M4/hqdefault.jpg"},{"channel":"Politico","title":"Trump suggests ABC News won't conduct 'fair debate' with Harris","url":"https://www.youtube.com/watch?v=mPwkJQgjXcA","id":"mPwkJQgjXcA","date":"4 days ago","thumbnail":"https://i.ytimg.com/vi/mPwkJQgjXcA/hqdefault.jpg"}]},{"channel-name":"C-SPAN","channel-id":"UCb--64Gl51jIEVE-GLDAVTg","channel-slug":"cspan","channel-url":"https://www.youtube.com/channel/UCb--64Gl51jIEVE-GLDAVTg/videos","channel-videos":[{"channel":"C-SPAN","title":"Washington Today (8-29-24): Army says ANC worker was 'abruptly pushed aside' by Trump campaign staff","url":"https://www.youtube.com/watch?v=R3yVwgnCWdc","id":"R3yVwgnCWdc","date":"19 hours ago","thumbnail":"https://i.ytimg.com/vi/R3yVwgnCWdc/hqdefault.jpg"},{"channel":"C-SPAN","title":"The Weekly Podcast: AI: History for Congress – and A New Voice for Jennifer Wexton","url":"https://www.youtube.com/watch?v=bW7H1COh938","id":"bW7H1COh938","date":"1 day ago","thumbnail":"https://i.ytimg.com/vi/bW7H1COh938/hqdefault.jpg"},{"channel":"C-SPAN","title":"Washington Today (8-27-24): GOP VP nominee JD Vance in MI; AFL-CIO's Liz Shuler on 'State of Unions'","url":"https://www.youtube.com/watch?v=5LTphX8qhGo","id":"5LTphX8qhGo","date":"2 days ago","thumbnail":"https://i.ytimg.com/vi/5LTphX8qhGo/hqdefault.jpg"},{"channel":"C-SPAN","title":"Washington Today (8-26-24): Donald Trump vows firings for Afghan bombing 'humiliation' 3 year ago","url":"https://www.youtube.com/watch?v=7Ntw1IbDhIs","id":"7Ntw1IbDhIs","date":"3 days ago","thumbnail":"https://i.ytimg.com/vi/7Ntw1IbDhIs/hqdefault.jpg"},{"channel":"C-SPAN","title":"Robert F. Kennedy, Jr. Suspends Campaign and Endorses Trump","url":"https://www.youtube.com/watch?v=R8_oZzKg338","id":"R8_oZzKg338","date":"6 days ago","thumbnail":"https://i.ytimg.com/vi/R8_oZzKg338/hqdefault.jpg"}]},{"channel-name":"Epoch TV","channel-id":"UCr9eziCDBtDANyWguKLr4vg","channel-slug":"epochtv","channel-url":"https://www.youtube.com/channel/UCr9eziCDBtDANyWguKLr4vg/videos","channel-videos":[]},{"channel-name":"Propublica","channel-id":"UCtCL58_DaVdVRmev3yHK7pg","channel-slug":"propublica","channel-url":"https://www.youtube.com/channel/UCtCL58_DaVdVRmev3yHK7pg/videos","channel-videos":[]},{"channel-name":"USA Today","channel-id":"UCP6HGa63sBC7-KHtkme-p-g","channel-slug":"usatoday","channel-url":"https://www.youtube.com/channel/UCP6HGa63sBC7-KHtkme-p-g/videos","channel-videos":[{"channel":"USA Today","title":"Donald Trump says he wants government or insurance companies to pay for IVF treatments | USA TODAY","url":"https://www.youtube.com/watch?v=6LOS2p205O8","id":"6LOS2p205O8","date":"1 hour ago","thumbnail":"https://i.ytimg.com/vi/6LOS2p205O8/hqdefault.jpg"}]},{"channel-name":"Forbes Breaking","channel-id":"UCg40OxZ1GYh3u3jBntB6DLg","channel-slug":"forbes","channel-url":"https://www.youtube.com/channel/UCg40OxZ1GYh3u3jBntB6DLg/videos","channel-videos":[{"channel":"Forbes Breaking","title":"Voters ‘Fairly Split’ On Biden’s Legacy As A One-Term President: Emerson Pollster Reveals","url":"https://www.youtube.com/watch?v=jmDhVFzfIbk","id":"jmDhVFzfIbk","date":"13 minutes ago","thumbnail":"https://i.ytimg.com/vi/jmDhVFzfIbk/hqdefault.jpg"},{"channel":"Forbes Breaking","title":"Voter Presses Donald Trump On Economic Plan At Town Hall: How Will You ‘Make Life More Affordable’?","url":"https://www.youtube.com/watch?v=bpiKlta8BlQ","id":"bpiKlta8BlQ","date":"28 minutes ago","thumbnail":"https://i.ytimg.com/vi/bpiKlta8BlQ/hqdefault.jpg"},{"channel":"Forbes Breaking","title":"'You Were Played By Every Country In The World': Trump Sounds Off On Harris's Foreign Policy Record","url":"https://www.youtube.com/watch?v=6GYqp3wmPTw","id":"6GYqp3wmPTw","date":"1 hour ago","thumbnail":"https://i.ytimg.com/vi/6GYqp3wmPTw/hqdefault.jpg"},{"channel":"Forbes Breaking","title":"'Appalls Me': Gold Star Mother Reacts To Trump Arlington Visit: Section 60 Should Not Be Politicized","url":"https://www.youtube.com/watch?v=ZBSCHeKD4ls","id":"ZBSCHeKD4ls","date":"1 hour ago","thumbnail":"https://i.ytimg.com/vi/ZBSCHeKD4ls/hqdefault.jpg"},{"channel":"Forbes Breaking","title":"Harris Pressed By Dana Bash On Trump's Economy: What Do ‘You Say To Voters Who Do Want To Go Back?’","url":"https://www.youtube.com/watch?v=I_0AgkH4rIU","id":"I_0AgkH4rIU","date":"1 hour ago","thumbnail":"https://i.ytimg.com/vi/I_0AgkH4rIU/hqdefault.jpg"},{"channel":"Forbes Breaking","title":"'Under Kamala, We Are Rapidly Approaching Economic And Social Catastrophe': Trump Shreds Harris","url":"https://www.youtube.com/watch?v=HnTJzTl-o5o","id":"HnTJzTl-o5o","date":"1 hour ago","thumbnail":"https://i.ytimg.com/vi/HnTJzTl-o5o/hqdefault.jpg"},{"channel":"Forbes Breaking","title":"'The Polls Are Rigged': Donald Trump Claims His Campaign Is 'Leading By A Lot'","url":"https://www.youtube.com/watch?v=R148DBTE8Ao","id":"R148DBTE8Ao","date":"2 hours ago","thumbnail":"https://i.ytimg.com/vi/R148DBTE8Ao/hqdefault.jpg"},{"channel":"Forbes Breaking","title":"'She's Been A Total Failure!': Donald Trump Tees Off On Kamala Harris's Record In Public Office","url":"https://www.youtube.com/watch?v=dPEBdP95k0M","id":"dPEBdP95k0M","date":"2 hours ago","thumbnail":"https://i.ytimg.com/vi/dPEBdP95k0M/hqdefault.jpg"}]},{"channel-name":"Valuetainment","channel-id":"UCIHdDJ0tjn_3j-FS7s_X1kQ","channel-slug":"Valuetainment","channel-url":"https://www.youtube.com/channel/UCIHdDJ0tjn_3j-FS7s_X1kQ/videos","channel-videos":[{"channel":"Valuetainment","title":"“Stupid & Unnecessary” - Chris Cuomo BLASTS Trump For Questioning Kamala Harris’ Race","url":"https://www.youtube.com/watch?v=HvHq_PeA-TU","id":"HvHq_PeA-TU","date":"1 hour ago","thumbnail":"https://i.ytimg.com/vi/HvHq_PeA-TU/hqdefault.jpg"},{"channel":"Valuetainment","title":"\"Weaponizes Masculinity\" - Young Men DITCH Democrats: Poll Shows MASSIVE Shift Toward GOP In 2024","url":"https://www.youtube.com/watch?v=CcWSpPCPu60","id":"CcWSpPCPu60","date":"3 hours ago","thumbnail":"https://i.ytimg.com/vi/CcWSpPCPu60/hqdefault.jpg"},{"channel":"Valuetainment","title":"“On Their Side” - Don Lemon SURPRISED By Black Voters Support For Trump","url":"https://www.youtube.com/watch?v=Q_OqakJKr7k","id":"Q_OqakJKr7k","date":"20 hours ago","thumbnail":"https://i.ytimg.com/vi/Q_OqakJKr7k/hqdefault.jpg"},{"channel":"Valuetainment","title":"“Real Political War” - Michigan NOT REMOVING RFK Jr. From Ballots","url":"https://www.youtube.com/watch?v=zdePfVdvIaY","id":"zdePfVdvIaY","date":"23 hours ago","thumbnail":"https://i.ytimg.com/vi/zdePfVdvIaY/hqdefault.jpg"},{"channel":"Valuetainment","title":"Kamala in Trouble? RFK Endorses Trump and Changes the Game! | The Decision Ep. 7","url":"https://www.youtube.com/watch?v=mgkno-m3E90","id":"mgkno-m3E90","date":"1 day ago","thumbnail":"https://i.ytimg.com/vi/mgkno-m3E90/hqdefault.jpg"}]}]}