{"retrieved-date":"2024-11-30T22:17:01.067Z","videos":[{"channel-name":"MettaCode Developers","channel-id":"UCUrW7YMZDBaVMjP7V3XnpVw","channel-slug":"mettacode","channel-url":"https://www.youtube.com/channel/UCUrW7YMZDBaVMjP7V3XnpVw/videos","channel-videos":[]},{"channel-name":"Capitol Babble","channel-id":"UC4X_dh5dgyC0d6T3KkjFTTQ","channel-slug":"capitolbabble","channel-url":"https://www.youtube.com/channel/UC4X_dh5dgyC0d6T3KkjFTTQ/videos","channel-videos":[]},{"channel-name":"Bloomberg Politics","channel-id":"UCV61VqLMr2eIhH4f51PV0gA","channel-slug":"bloomberg","channel-url":"https://www.youtube.com/channel/UCV61VqLMr2eIhH4f51PV0gA/videos","channel-videos":[]},{"channel-name":"Politico","channel-id":"UCgjtvMmHXbutALaw9XzRkAg","channel-slug":"politico","channel-url":"https://www.youtube.com/channel/UCgjtvMmHXbutALaw9XzRkAg/videos","channel-videos":[{"channel":"Politico","title":"Meet Kristi Noem, Trump's DHS pick","url":"https://www.youtube.com/watch?v=3T-yyA9yg1s","id":"3T-yyA9yg1s","date":"3 days ago","thumbnail":"https://i.ytimg.com/vi/3T-yyA9yg1s/hqdefault.jpg"},{"channel":"Politico","title":"Meet RFK Jr., Trump's pick to lead HHS","url":"https://www.youtube.com/watch?v=8pK2hQJGAX0","id":"8pK2hQJGAX0","date":"8 days ago","thumbnail":"https://i.ytimg.com/vi/8pK2hQJGAX0/hqdefault.jpg"},{"channel":"Politico","title":"AG nominee Matt Gaetz says meetings with GOP senators 'going great'","url":"https://www.youtube.com/watch?v=6dshnssEnUM","id":"6dshnssEnUM","date":"9 days ago","thumbnail":"https://i.ytimg.com/vi/6dshnssEnUM/hqdefault.jpg"},{"channel":"Politico","title":"Meet Tom Homan, Trump's 'border czar'","url":"https://www.youtube.com/watch?v=ruUWOoU2hfQ","id":"ruUWOoU2hfQ","date":"12 days ago","thumbnail":"https://i.ytimg.com/vi/ruUWOoU2hfQ/hqdefault.jpg"}]},{"channel-name":"C-SPAN","channel-id":"UCb--64Gl51jIEVE-GLDAVTg","channel-slug":"cspan","channel-url":"https://www.youtube.com/channel/UCb--64Gl51jIEVE-GLDAVTg/videos","channel-videos":[{"channel":"C-SPAN","title":"Washington Today (11-27-24): Israel-Hezbollah ceasefire holds; Trump Cabinet nominees get threats","url":"https://www.youtube.com/watch?v=vMRQaeK5K_4","id":"vMRQaeK5K_4","date":"2 days ago","thumbnail":"https://i.ytimg.com/vi/vMRQaeK5K_4/hqdefault.jpg"},{"channel":"C-SPAN","title":"Washington Today (11-26-24): President Biden announces Israel-Hezbollah ceasefire deal","url":"https://www.youtube.com/watch?v=FsPDxxvRqZE","id":"FsPDxxvRqZE","date":"3 days ago","thumbnail":"https://i.ytimg.com/vi/FsPDxxvRqZE/hqdefault.jpg"},{"channel":"C-SPAN","title":"President Biden on Israel-Hezbollah Ceasefire Deal","url":"https://www.youtube.com/watch?v=4FbrDHOV6VI","id":"4FbrDHOV6VI","date":"4 days ago","thumbnail":"https://i.ytimg.com/vi/4FbrDHOV6VI/hqdefault.jpg"},{"channel":"C-SPAN","title":"Washington Today (11/25/24): Jack Smith drops federal election cases against Donald Trump","url":"https://www.youtube.com/watch?v=OVR55DJnz64","id":"OVR55DJnz64","date":"4 days ago","thumbnail":"https://i.ytimg.com/vi/OVR55DJnz64/hqdefault.jpg"},{"channel":"C-SPAN","title":"Washington Today (11-22-24): Ex-Attorney General nominee Matt Gaetz says he won't return to Congress","url":"https://www.youtube.com/watch?v=PpEqMlMFeY0","id":"PpEqMlMFeY0","date":"7 days ago","thumbnail":"https://i.ytimg.com/vi/PpEqMlMFeY0/hqdefault.jpg"},{"channel":"C-SPAN","title":"Washington Today (11-21-24): Matt Gaetz withdraws nomination to be Attorney General in Trump Admin.","url":"https://www.youtube.com/watch?v=o0p0YLB-ziY","id":"o0p0YLB-ziY","date":"8 days ago","thumbnail":"https://i.ytimg.com/vi/o0p0YLB-ziY/hqdefault.jpg"},{"channel":"C-SPAN","title":"Washington Today (11-20-24): House Ethics Cmte in partisan tie vote does not release Gaetz report","url":"https://www.youtube.com/watch?v=skigp-GxVho","id":"skigp-GxVho","date":"9 days ago","thumbnail":"https://i.ytimg.com/vi/skigp-GxVho/hqdefault.jpg"}]},{"channel-name":"Epoch TV","channel-id":"UCr9eziCDBtDANyWguKLr4vg","channel-slug":"epochtv","channel-url":"https://www.youtube.com/channel/UCr9eziCDBtDANyWguKLr4vg/videos","channel-videos":[]},{"channel-name":"Propublica","channel-id":"UCtCL58_DaVdVRmev3yHK7pg","channel-slug":"propublica","channel-url":"https://www.youtube.com/channel/UCtCL58_DaVdVRmev3yHK7pg/videos","channel-videos":[{"channel":"Propublica","title":"How Donald Trump Plans to Take Spending Control From Congress","url":"https://www.youtube.com/watch?v=loC-UTFPizQ","id":"loC-UTFPizQ","date":"3 days ago","thumbnail":"https://i.ytimg.com/vi/loC-UTFPizQ/hqdefault.jpg"}]},{"channel-name":"USA Today","channel-id":"UCP6HGa63sBC7-KHtkme-p-g","channel-slug":"usatoday","channel-url":"https://www.youtube.com/channel/UCP6HGa63sBC7-KHtkme-p-g/videos","channel-videos":[{"channel":"USA Today","title":"Canadian Prime Minister Trudeau visits Trump for tariff talk | The Excerpt","url":"https://www.youtube.com/watch?v=f2w9ZOtLI_E","id":"f2w9ZOtLI_E","date":"10 hours ago","thumbnail":"https://i.ytimg.com/vi/f2w9ZOtLI_E/hqdefault.jpg"},{"channel":"USA Today","title":"Trump, Sheinbaum talk border security as tariff threat looms | The Excerpt","url":"https://www.youtube.com/watch?v=1VfpOdwW_ys","id":"1VfpOdwW_ys","date":"1 day ago","thumbnail":"https://i.ytimg.com/vi/1VfpOdwW_ys/hqdefault.jpg"}]},{"channel-name":"Forbes Breaking","channel-id":"UCg40OxZ1GYh3u3jBntB6DLg","channel-slug":"forbes","channel-url":"https://www.youtube.com/channel/UCg40OxZ1GYh3u3jBntB6DLg/videos","channel-videos":[{"channel":"Forbes Breaking","title":"Top Critic Matt Gaetz Doesn’t Let Up Grilling Witnesses On The ‘Biden Crime Family’ | 2024 Rewind","url":"https://www.youtube.com/watch?v=wIboRny1ozI","id":"wIboRny1ozI","date":"2 minutes ago","thumbnail":"https://i.ytimg.com/vi/wIboRny1ozI/hqdefault.jpg"},{"channel":"Forbes Breaking","title":"SUPERCUT: Alina Habba Torches Democrats, Uncompromisingly Defends Trump | 2024 Rewind","url":"https://www.youtube.com/watch?v=96nmVTO9W_8","id":"96nmVTO9W_8","date":"32 minutes ago","thumbnail":"https://i.ytimg.com/vi/96nmVTO9W_8/hqdefault.jpg"},{"channel":"Forbes Breaking","title":"Thomas Massie Delivers A Flurry Of Fiery Speeches On The House Floor | 2024 Rewind","url":"https://www.youtube.com/watch?v=UuFG_An_YGo","id":"UuFG_An_YGo","date":"1 hour ago","thumbnail":"https://i.ytimg.com/vi/UuFG_An_YGo/hqdefault.jpg"},{"channel":"Forbes Breaking","title":"'We Must Reverse The Damage Of The Biden Administration': Chip Roy Demands GOP Border Legislation","url":"https://www.youtube.com/watch?v=qZRyXkaUhr0","id":"qZRyXkaUhr0","date":"1 hour ago","thumbnail":"https://i.ytimg.com/vi/qZRyXkaUhr0/hqdefault.jpg"},{"channel":"Forbes Breaking","title":"SUPERCUT: Ted Cruz Goes Nuclear On Biden-Harris Administration, Democrats Over Border | 2024 Rewind","url":"https://www.youtube.com/watch?v=APwGnXzHNeE","id":"APwGnXzHNeE","date":"3 hours ago","thumbnail":"https://i.ytimg.com/vi/APwGnXzHNeE/hqdefault.jpg"}]},{"channel-name":"Valuetainment","channel-id":"UCIHdDJ0tjn_3j-FS7s_X1kQ","channel-slug":"Valuetainment","channel-url":"https://www.youtube.com/channel/UCIHdDJ0tjn_3j-FS7s_X1kQ/videos","channel-videos":[]}]}