{"retrieved-date":"2024-05-20T01:50:28.090Z","videos":[{"channel-name":"MettaCode Developers","channel-id":"UCUrW7YMZDBaVMjP7V3XnpVw","channel-slug":"mettacode","channel-url":"https://www.youtube.com/channel/UCUrW7YMZDBaVMjP7V3XnpVw/videos","channel-videos":[]},{"channel-name":"Capitol Babble","channel-id":"UC4X_dh5dgyC0d6T3KkjFTTQ","channel-slug":"capitolbabble","channel-url":"https://www.youtube.com/channel/UC4X_dh5dgyC0d6T3KkjFTTQ/videos","channel-videos":[]},{"channel-name":"Bloomberg Politics","channel-id":"UCV61VqLMr2eIhH4f51PV0gA","channel-slug":"bloomberg","channel-url":"https://www.youtube.com/channel/UCV61VqLMr2eIhH4f51PV0gA/videos","channel-videos":[]},{"channel-name":"Politico","channel-id":"UCgjtvMmHXbutALaw9XzRkAg","channel-slug":"politico","channel-url":"https://www.youtube.com/channel/UCgjtvMmHXbutALaw9XzRkAg/videos","channel-videos":[{"channel":"Politico","title":"Gaetz, Boebert and others defend Trump outside hush money trial","url":"https://www.youtube.com/watch?v=ZseE8jEZj4w","id":"ZseE8jEZj4w","date":"3 days ago","thumbnail":"https://i.ytimg.com/vi/ZseE8jEZj4w/hqdefault.jpg"},{"channel":"Politico","title":"Dems slam GOP effort to hold Garland in contempt over Biden audio","url":"https://www.youtube.com/watch?v=EqWBUrVt0L0","id":"EqWBUrVt0L0","date":"3 days ago","thumbnail":"https://i.ytimg.com/vi/EqWBUrVt0L0/hqdefault.jpg"},{"channel":"Politico","title":"‘Sham’: GOP comes to Trump’s defense outside courthouse","url":"https://www.youtube.com/watch?v=69e6kL6nKqQ","id":"69e6kL6nKqQ","date":"5 days ago","thumbnail":"https://i.ytimg.com/vi/69e6kL6nKqQ/hqdefault.jpg"},{"channel":"Politico","title":"GOP lawmakers defend Trump outside hush money trial","url":"https://www.youtube.com/watch?v=TDLmlLKPSFs","id":"TDLmlLKPSFs","date":"6 days ago","thumbnail":"https://i.ytimg.com/vi/TDLmlLKPSFs/hqdefault.jpg"},{"channel":"Politico","title":"Stormy Daniels had no filter at Trump trial, here's what happened","url":"https://www.youtube.com/watch?v=8tIzXnJYXJw","id":"8tIzXnJYXJw","date":"6 days ago","thumbnail":"https://i.ytimg.com/vi/8tIzXnJYXJw/hqdefault.jpg"},{"channel":"Politico","title":"UN votes to revive Palestinian membership bid, despite US opposition","url":"https://www.youtube.com/watch?v=rdMW1qe0-Wg","id":"rdMW1qe0-Wg","date":"9 days ago","thumbnail":"https://i.ytimg.com/vi/rdMW1qe0-Wg/hqdefault.jpg"},{"channel":"Politico","title":"Congress at odds over Biden pausing weapons shipments to Israel","url":"https://www.youtube.com/watch?v=Y6kfimE8tTA","id":"Y6kfimE8tTA","date":"10 days ago","thumbnail":"https://i.ytimg.com/vi/Y6kfimE8tTA/hqdefault.jpg"},{"channel":"Politico","title":"Rep. Lawler: Roy, Massie should be removed from committee for Johnson 'stunt'","url":"https://www.youtube.com/watch?v=7X8e1l93l34","id":"7X8e1l93l34","date":"10 days ago","thumbnail":"https://i.ytimg.com/vi/7X8e1l93l34/hqdefault.jpg"},{"channel":"Politico","title":"Judge threatens Trump with jail time, here's what happened","url":"https://www.youtube.com/watch?v=sMr2ZSzlD7o","id":"sMr2ZSzlD7o","date":"10 days ago","thumbnail":"https://i.ytimg.com/vi/sMr2ZSzlD7o/hqdefault.jpg"}]},{"channel-name":"C-SPAN","channel-id":"UCb--64Gl51jIEVE-GLDAVTg","channel-slug":"cspan","channel-url":"https://www.youtube.com/channel/UCb--64Gl51jIEVE-GLDAVTg/videos","channel-videos":[{"channel":"C-SPAN","title":"2024 Campaign Trail: RFK Jr. in Texas & Pennsylvania's U.S. Senate Race","url":"https://www.youtube.com/watch?v=KAMXVL1TS4U","id":"KAMXVL1TS4U","date":"2 days ago","thumbnail":"https://i.ytimg.com/vi/KAMXVL1TS4U/hqdefault.jpg"},{"channel":"C-SPAN","title":"RFK Jr. in Texas & Pennsylvania's U.S. Senate Race","url":"https://www.youtube.com/watch?v=ooZWTsFrmkc","id":"ooZWTsFrmkc","date":"2 days ago","thumbnail":"https://i.ytimg.com/vi/ooZWTsFrmkc/hqdefault.jpg"},{"channel":"C-SPAN","title":"Washington Today (5-17-24): House bill says defund police calls leads to violence against officers","url":"https://www.youtube.com/watch?v=oE_dj8gf6rM","id":"oE_dj8gf6rM","date":"2 days ago","thumbnail":"https://i.ytimg.com/vi/oE_dj8gf6rM/hqdefault.jpg"},{"channel":"C-SPAN","title":"Washington Today (5-16-24): White House asserts executive privilege over President's interview audio","url":"https://www.youtube.com/watch?v=6MwgUzwriv0","id":"6MwgUzwriv0","date":"3 days ago","thumbnail":"https://i.ytimg.com/vi/6MwgUzwriv0/hqdefault.jpg"},{"channel":"C-SPAN","title":"Speaker Johnson on President Biden Invoking Executive Privilege","url":"https://www.youtube.com/watch?v=JMyDrXuNUw4","id":"JMyDrXuNUw4","date":"3 days ago","thumbnail":"https://i.ytimg.com/vi/JMyDrXuNUw4/hqdefault.jpg"},{"channel":"C-SPAN","title":"Washington Today (5-15-24): Joe Biden & Donald Trump agree to two presidential debates, on CNN & ABC","url":"https://www.youtube.com/watch?v=zB6cM9IgGlA","id":"zB6cM9IgGlA","date":"4 days ago","thumbnail":"https://i.ytimg.com/vi/zB6cM9IgGlA/hqdefault.jpg"}]},{"channel-name":"Epoch TV","channel-id":"UCr9eziCDBtDANyWguKLr4vg","channel-slug":"epochtv","channel-url":"https://www.youtube.com/channel/UCr9eziCDBtDANyWguKLr4vg/videos","channel-videos":[{"channel":"Epoch TV","title":"Poll Shows Trump Taking All But One Swing State, Biden Facing Clash With Donors Over Israel | CLIP","url":"https://www.youtube.com/watch?v=kbRiZosDKzc","id":"kbRiZosDKzc","date":"3 days ago","thumbnail":"https://i.ytimg.com/vi/kbRiZosDKzc/hqdefault.jpg"}]},{"channel-name":"Propublica","channel-id":"UCtCL58_DaVdVRmev3yHK7pg","channel-slug":"propublica","channel-url":"https://www.youtube.com/channel/UCtCL58_DaVdVRmev3yHK7pg/videos","channel-videos":[{"channel":"Propublica","title":"Trump Could Face $100M+ Tax Bill Connected to His Chicago Tower","url":"https://www.youtube.com/watch?v=SVqiPCf1yMk","id":"SVqiPCf1yMk","date":"8 days ago","thumbnail":"https://i.ytimg.com/vi/SVqiPCf1yMk/hqdefault.jpg"}]},{"channel-name":"USA Today","channel-id":"UCP6HGa63sBC7-KHtkme-p-g","channel-slug":"usatoday","channel-url":"https://www.youtube.com/channel/UCP6HGa63sBC7-KHtkme-p-g/videos","channel-videos":[{"channel":"USA Today","title":"Biden invokes executive privilege to shield Hur interview tapes from House | The Excerpt","url":"https://www.youtube.com/watch?v=0iqOtbazNxk","id":"0iqOtbazNxk","date":"2 days ago","thumbnail":"https://i.ytimg.com/vi/0iqOtbazNxk/hqdefault.jpg"},{"channel":"USA Today","title":"Biden invokes executive privilege to protect tapes of his deposition from being released | USA TODAY","url":"https://www.youtube.com/watch?v=3ZRtBnrJxWw","id":"3ZRtBnrJxWw","date":"3 days ago","thumbnail":"https://i.ytimg.com/vi/3ZRtBnrJxWw/hqdefault.jpg"}]},{"channel-name":"Forbes Breaking","channel-id":"UCg40OxZ1GYh3u3jBntB6DLg","channel-slug":"forbes","channel-url":"https://www.youtube.com/channel/UCg40OxZ1GYh3u3jBntB6DLg/videos","channel-videos":[{"channel":"Forbes Breaking","title":"Jason Smith Promotes Bill To Secure Taxpayer Information After Bombshell IRS Data Leak Case","url":"https://www.youtube.com/watch?v=obruE78-6bE","id":"obruE78-6bE","date":"20 minutes ago","thumbnail":"https://i.ytimg.com/vi/obruE78-6bE/hqdefault.jpg"},{"channel":"Forbes Breaking","title":"Michelle Fischbach: 'President Trump Knows That Minnesota Is In Play This Year'","url":"https://www.youtube.com/watch?v=-xc9EOqyBAQ","id":"-xc9EOqyBAQ","date":"27 minutes ago","thumbnail":"https://i.ytimg.com/vi/-xc9EOqyBAQ/hqdefault.jpg"},{"channel":"Forbes Breaking","title":"Biden Castigates Trump In Remarks To NAACP Fight for Freedom Fund Dinner In Detroit, Michigan","url":"https://www.youtube.com/watch?v=SSfq0Av7Tgo","id":"SSfq0Av7Tgo","date":"30 minutes ago","thumbnail":"https://i.ytimg.com/vi/SSfq0Av7Tgo/hqdefault.jpg"},{"channel":"Forbes Breaking","title":"Biden Calls For 'Immediate Ceasefire' In Gaza And Says He's 'Working On A Deal' At Morehouse College","url":"https://www.youtube.com/watch?v=WJnISGm-oRc","id":"WJnISGm-oRc","date":"54 minutes ago","thumbnail":"https://i.ytimg.com/vi/WJnISGm-oRc/hqdefault.jpg"},{"channel":"Forbes Breaking","title":"Trump Predicts Democrats Are 'Going To Do A Zoom Convention' At 2024 DNC In Remarks To NRA Forum","url":"https://www.youtube.com/watch?v=zCIlPDL-QhA","id":"zCIlPDL-QhA","date":"1 hour ago","thumbnail":"https://i.ytimg.com/vi/zCIlPDL-QhA/hqdefault.jpg"},{"channel":"Forbes Breaking","title":"Biden Tells Morehouse College Graduates That Republicans 'Don't See You In The Future Of America'","url":"https://www.youtube.com/watch?v=YWs5ImjyDVo","id":"YWs5ImjyDVo","date":"3 hours ago","thumbnail":"https://i.ytimg.com/vi/YWs5ImjyDVo/hqdefault.jpg"},{"channel":"Forbes Breaking","title":"'He Is So Full Of S---': Trump Goes On Angry Rant Over Biden's Offer To Play Golf Against Him","url":"https://www.youtube.com/watch?v=kPjF9SSwe1E","id":"kPjF9SSwe1E","date":"3 hours ago","thumbnail":"https://i.ytimg.com/vi/kPjF9SSwe1E/hqdefault.jpg"}]},{"channel-name":"Valuetainment","channel-id":"UCIHdDJ0tjn_3j-FS7s_X1kQ","channel-slug":"Valuetainment","channel-url":"https://www.youtube.com/channel/UCIHdDJ0tjn_3j-FS7s_X1kQ/videos","channel-videos":[{"channel":"Valuetainment","title":"\"Voting AGAINST Biden\" - Poll Predicts Trump Flips FIVE Swing States & Wins Electoral College","url":"https://www.youtube.com/watch?v=dAsRv9FV2XM","id":"dAsRv9FV2XM","date":"3 days ago","thumbnail":"https://i.ytimg.com/vi/dAsRv9FV2XM/hqdefault.jpg"},{"channel":"Valuetainment","title":"“They’re Outsiders” - Eduardo Bolsonaro Explains Why Voters LOVE Javier Milei & Jair Bolsonaro","url":"https://www.youtube.com/watch?v=BW7_jZ-I20g","id":"BW7_jZ-I20g","date":"3 days ago","thumbnail":"https://i.ytimg.com/vi/BW7_jZ-I20g/hqdefault.jpg"},{"channel":"Valuetainment","title":"“Roaring Kitty is BACK!” - GME Explodes As GameStop’s Stock SOARS with Return of Meme Stock Rally","url":"https://www.youtube.com/watch?v=M3ybui2X6Ac","id":"M3ybui2X6Ac","date":"4 days ago","thumbnail":"https://i.ytimg.com/vi/M3ybui2X6Ac/hqdefault.jpg"},{"channel":"Valuetainment","title":"\"Political Hit Job\" - Convicted Felon Michael Cohen's Secret Trump Tape Played At Hush Money Trial","url":"https://www.youtube.com/watch?v=S0HT-iORAQ0","id":"S0HT-iORAQ0","date":"4 days ago","thumbnail":"https://i.ytimg.com/vi/S0HT-iORAQ0/hqdefault.jpg"},{"channel":"Valuetainment","title":"\"Trump Was Right\" - CNN Anchor FORCED To Admit Trump's Immigration Policies Better Than Biden's","url":"https://www.youtube.com/watch?v=m9xAeLMmYFM","id":"m9xAeLMmYFM","date":"4 days ago","thumbnail":"https://i.ytimg.com/vi/m9xAeLMmYFM/hqdefault.jpg"},{"channel":"Valuetainment","title":"\"No More Lip Service\" - Ice Cube Says Black Voters Want Politicians to Put America First","url":"https://www.youtube.com/watch?v=qlYcozbD2Gg","id":"qlYcozbD2Gg","date":"4 days ago","thumbnail":"https://i.ytimg.com/vi/qlYcozbD2Gg/hqdefault.jpg"}]}]}